eheso_api_client/__init__.py
eheso_api_client/api_client.py
eheso_api_client/api_response.py
eheso_api_client/configuration.py
eheso_api_client/exceptions.py
eheso_api_client/py.typed
eheso_api_client/rest.py
eheso_api_client/api/__init__.py
eheso_api_client/api/country_data_api.py
eheso_api_client/api/field_info_api.py
eheso_api_client/api/layer_data_api.py
eheso_api_client/api/layer_info_api.py
eheso_api_client/models/__init__.py
eheso_api_client/models/error_schema.py
eheso_api_client/models/export_schema.py
eheso_api_client/models/export_schema_all_of_file_export.py
eheso_api_client/models/field200_response.py
eheso_api_client/models/field_info_basic_response.py
eheso_api_client/models/field_info_basic_response_info.py
eheso_api_client/models/field_info_detailed_response.py
eheso_api_client/models/field_info_detailed_response_info.py
eheso_api_client/models/format.py
eheso_api_client/models/layer_response_inner.py
eheso_api_client/models/query_post_schema.py
eheso_api_client/models/query_post_schema_sort_value.py
eheso_api_client-0.2.1.dist-info/METADATA
eheso_api_client-0.2.1.dist-info/WHEEL
eheso_api_client-0.2.1.dist-info/top_level.txt
eheso_api_client-0.2.1.dist-info/RECORD
