Metadata-Version: 2.1
Name: eheso-api-client
Version: 0.2.1
Summary: EHESO API
Home-page: UNKNOWN
Author: OpenAPI Generator community
Author-email: team@openapitools.org
License: UNKNOWN
Keywords: OpenAPI,OpenAPI-Generator,EHESO API
Platform: UNKNOWN
Requires-Dist: aenum
Requires-Dist: pydantic<2,>=1.10.5
Requires-Dist: python-dateutil
Requires-Dist: python-dotenv>=1.0.1
Requires-Dist: urllib3<2.1.0,>=1.25.3
